openapi_to_markdown/__init__.py
openapi_to_markdown/converter.py
openapi_to_markdown/templates/_content.md.j2
openapi_to_markdown/templates/_example.md.j2
openapi_to_markdown/templates/_object_schema.md.j2
openapi_to_markdown/templates/_security_scheme.md.j2
openapi_to_markdown/templates/base.md.jinja
openapi_to_md-0.1.0b2.dist-info/LICENSE
openapi_to_md-0.1.0b2.dist-info/METADATA
openapi_to_md-0.1.0b2.dist-info/WHEEL
openapi_to_md-0.1.0b2.dist-info/entry_points.txt
openapi_to_md-0.1.0b2.dist-info/RECORD
