Metadata-Version: 2.3
Name: openapi-to-md
Version: 0.1.0b2
Summary: 
Author: dayoungMM
Author-email: dalbeetm@gmail.com
Requires-Python: >=3.10,<4.0
Classifier: Programming Language :: Python :: 3
Classifier: Programming Language :: Python :: 3.10
Classifier: Programming Language :: Python :: 3.11
Classifier: Programming Language :: Python :: 3.12
Classifier: Programming Language :: Python :: 3.13
Requires-Dist: click (>=8.1.7,<9.0.0)
Requires-Dist: jinja2 (>=3.1.4,<4.0.0)
Requires-Dist: pyyaml (>=6.0.1,<7.0.0)
